basic/__init__.py
code/__init__.py
code/basic/__init__.py
code/config/EmLogCfg.py
code/config/EmLogCfgReader.py
code/config/EmLogEnums.py
code/config/LogCfgToken.py
code/config/__init__.py
code/spantrace/__init__.py
config/EmLogCfg.py
config/EmLogCfgReader.py
config/EmLogEnums.py
config/__init__.py
spantrace/__init__.py
emlog-0.5.dist-info/METADATA
emlog-0.5.dist-info/WHEEL
emlog-0.5.dist-info/top_level.txt
emlog-0.5.dist-info/RECORD
