Metadata-Version: 2.1
Name: emlog
Version: 0.5
Summary: python版本日志组件
Home-page: https://github.com/frankli/emlog
Author: 李栋
Author-email: frankli715@qq.com
